llama_index/py.typed
llama_index/vector_stores/ApertureDB/__init__.py
llama_index/vector_stores/ApertureDB/base.py
llama_index_vector_stores_aperturedb-0.1.1.dist-info/METADATA
llama_index_vector_stores_aperturedb-0.1.1.dist-info/WHEEL
llama_index_vector_stores_aperturedb-0.1.1.dist-info/RECORD
