Metadata-Version: 2.4
Name: llama-index-vector-stores-ApertureDB
Version: 0.1.1
Summary: llama-index vector_stores ApertureDB integration
Author-email: ApertureData <team@aperturedata.io>
License-Expression: MIT
Requires-Python: <3.13,>=3.10
Requires-Dist: aperturedb>=0.4.45
Requires-Dist: llama-index-core<0.15,>=0.13.0
Provides-Extra: fastembed
